[
	{ "s": "Д", "p": [188, 82, 189, 106, 64, 185, 179, 131, 125, 121, 98, 83, 25, 19, 15, 13, 8] },
	{ "s": "Д.Г", "p": [189] },
	{ "s": "ДАВЛЕНИЕ", "p": [131, 118, 164, 127, 124, 125, 121, 85] },
	{ "s": "ДАВЛЕНИЕМ", "p": [125, 129, 127, 130, 124, 121, 118] },
	{ "s": "ДАВЛЕНИИ", "p": [121, 126, 118] },
	{ "s": "ДАВЛЕНИЯ", "p": [164, 116, 121, 133, 55, 48, 26, 25] },
	{ "s": "ДАЕТ", "p": [42] },
	{ "s": "ДАЕТСЯ", "p": [127, 84, 81] },
	{ "s": "ДАЛЕЕ", "p": [132, 190, 187, 71, 25, 192, 188, 141, 137, 130, 127, 126, 119, 79, 73, 72, 49, 16, 14, 12, 11, 8, 4] },
	{ "s": "ДАЛЬНЕВОСТОЧНОМ", "p": [115] },
	{ "s": "ДАЛЬНЕЙШЕГО", "p": [15, 42, 24] },
	{ "s": "ДАЛЬНЕЙШЕЕ", "p": [123, 15] },
	{ "s": "ДАЛЬНЕЙШЕЙ", "p": [121, 108, 8, 5] },
	{ "s": "ДАЛЬНЕЙШЕМ", "p": [19, 81, 42, 27] },
	{ "s": "ДАЛЬНЕЙШЕМУ", "p": [80, 42, 24, 11] },
	{ "s": "ДАЛЬНЕЙШИЙ", "p": [83] },
	{ "s": "ДАЛЬНОСТЬ", "p": [84] },
	{ "s": "ДАНА", "p": [127, 108] },
	{ "s": "ДАННАЯ", "p": [71, 19] },
	{ "s": "ДАННОГО", "p": [18, 137, 111, 97, 83, 25, 15] },
	{ "s": "ДАННОЙ", "p": [171, 25, 71, 34, 19] },
	{ "s": "ДАННОМ", "p": [179, 20, 185, 146, 105, 97] },
	{ "s": "ДАННОМУ", "p": [186, 106] },
	{ "s": "ДАННУЮ", "p": [150, 86, 71, 49, 19] },
	{ "s": "ДАННЫЕ", "p": [85, 83, 86, 84, 27, 109, 106, 181, 168, 167, 166, 131, 125, 118, 113, 81, 77, 16, 9] },
	{ "s": "ДАННЫЙ", "p": [81, 66, 3] },
	{ "s": "ДАННЫМ", "p": [11, 172, 118, 64, 59, 58, 30, 24, 19, 15] },
	{ "s": "ДАННЫМИ", "p": [84, 9, 179, 134, 121, 107, 106, 105, 86, 82, 38, 27, 11] },
	{ "s": "ДАННЫХ", "p": [11, 16, 85, 82, 73, 71, 64, 62, 59, 58, 55, 28, 9, 8] },
	{ "s": "ДАТА", "p": [85, 83, 84, 98, 180, 131, 97, 86, 82, 81, 186, 172, 113, 107, 105, 104, 179, 118, 110, 91, 156, 111, 102, 100, 93, 192, 191, 169, 163, 158, 124, 120, 112, 109, 108, 106, 95, 27, 26, 25, 17, 15] },
	{ "s": "ДАТЕ", "p": [181] },
	{ "s": "ДАТОЙ", "p": [140] },
	{ "s": "ДАТУ", "p": [85, 131, 118, 134, 15] },
	{ "s": "ДАТЧИК", "p": [116] },
	{ "s": "ДАТЧИКА", "p": [113] },
	{ "s": "ДАТЫ", "p": [169, 83, 111, 107, 91, 86, 85, 71, 67, 59, 58] },
	{ "s": "ДАТЬ", "p": [140] },
	{ "s": "ДВА", "p": [183, 160, 138, 122, 25] },
	{ "s": "ДВАДЦАТЬ", "p": [2] },
	{ "s": "ДВЕ", "p": [101, 183, 132, 126, 118, 85, 84, 58, 11] },
	{ "s": "ДВЕРЕЙ", "p": [147, 156, 133, 141, 98, 79, 19, 11] },
	{ "s": "ДВЕРИ", "p": [183, 148, 141, 140, 79, 184, 154, 147, 116, 58, 50, 23] },
	{ "s": "ДВЕРНОЙ", "p": [184] },
	{ "s": "ДВЕРНЫЕ", "p": [141, 79] },
	{ "s": "ДВЕРНЫХ", "p": [61, 57] },
	{ "s": "ДВЕРЬ", "p": [116] },
	{ "s": "ДВЕРЯХ", "p": [140, 50] },
	{ "s": "ДВИГАТЕЛЕЙ", "p": [11, 85, 83, 138, 137, 133, 84, 23, 161, 136, 96, 46, 21] },
	{ "s": "ДВИГАТЕЛЕМ", "p": [21, 18] },
	{ "s": "ДВИГАТЕЛИ", "p": [84, 83, 81, 14] },
	{ "s": "ДВИГАТЕЛЬ", "p": [84, 83, 115, 108, 116, 98, 96, 27] },
	{ "s": "ДВИГАТЕЛЬ(И", "p": [84] },
	{ "s": "ДВИГАТЕЛЯ", "p": [25, 83, 84, 138, 105, 107, 97, 86, 168, 164, 140, 137, 98, 85, 81, 48, 27, 23, 21, 18, 17, 3] },
	{ "s": "ДВИГАТЕЛЯ(Й", "p": [83] },
	{ "s": "ДВИГАТЕЛЯМИ", "p": [23] },
	{ "s": "ДВИЖЕНИЕ", "p": [85, 147, 131, 84, 46, 3] },
	{ "s": "ДВИЖЕНИЕМ", "p": [144] },
	{ "s": "ДВИЖЕНИИ", "p": [16, 190, 144, 84, 82, 24] },
	{ "s": "ДВИЖЕНИЮ", "p": [32] },
	{ "s": "ДВИЖЕНИЯ", "p": [19, 133, 82, 190, 110, 27, 11, 144, 86, 61, 24, 16, 181, 180, 135, 132, 131, 124, 118, 93, 92, 91, 89, 57, 37, 29, 25, 20, 8, 3] },
	{ "s": "ДВИЖИМОГО", "p": [8] },
	{ "s": "ДВИЖИТЕЛЕЙ", "p": [83, 11] },
	{ "s": "ДВИЖИТЕЛЮ", "p": [83] },
	{ "s": "ДВОЙНУЮ", "p": [125] },
	{ "s": "ДВОЙНЫМИ", "p": [140] },
	{ "s": "ДВОРУ", "p": [124] },
	{ "s": "ДВУКРАТНОГО", "p": [131] },
	{ "s": "ДВУМЯ", "p": [127, 109, 86] },
	{ "s": "ДВУСТВОРЧАТЫЕ", "p": [58] },
	{ "s": "ДВУСТВОРЧАТЫХ", "p": [152] },
	{ "s": "ДВУСТОРОННЕМ", "p": [144] },
	{ "s": "ДВУСТОРОННИЙ", "p": [164, 133] },
	{ "s": "ДВУСТОРОННИМ", "p": [144] },
	{ "s": "ДВУХ", "p": [101, 138, 81, 19, 186, 160, 127, 113, 112, 108, 107, 91, 86, 70, 67, 29, 26, 11] },
	{ "s": "ДВУХРЯДНОГО", "p": [138] },
	{ "s": "ДВУХСТОРОННЕЙ", "p": [91] },
	{ "s": "ДВУХЪЯРУСНЫХ", "p": [140] },
	{ "s": "ДЕЖУРНО", "p": [11] },
	{ "s": "ДЕЖУРНО-ДИСПЕТЧЕРСКОЙ", "p": [11] },
	{ "s": "ДЕЖУРНОГО", "p": [147, 133, 57, 155, 145, 141, 11, 184, 79, 61, 177, 174, 173, 167, 162, 159, 157, 156, 148, 26, 20, 19] },
	{ "s": "ДЕЖУРНОЙ", "p": [184, 61, 26, 147, 141, 79, 21, 148, 145, 60] },
	{ "s": "ДЕЖУРНОМУ", "p": [147, 184, 155] },
	{ "s": "ДЕЖУРНУЮ", "p": [20] },
	{ "s": "ДЕЖУРНЫЕ", "p": [92, 19] },
	{ "s": "ДЕЖУРНЫЙ", "p": [147, 86, 42, 19] },
	{ "s": "ДЕЖУРНЫМ", "p": [150, 147, 133, 111, 63] },
	{ "s": "ДЕЖУРНЫХ", "p": [21, 139, 26, 147, 133, 155, 132, 57, 25, 20, 19, 11] },
	{ "s": "ДЕЖУРСТВ", "p": [26] },
	{ "s": "ДЕЖУРСТВА", "p": [26, 89, 57, 21, 133, 64, 61, 60, 59, 58, 56, 29, 23, 19] },
	{ "s": "ДЕЖУРСТВЕ", "p": [11] },
	{ "s": "ДЕЖУРСТВО", "p": [57, 37, 26, 61, 60, 24] },
	{ "s": "ДЕЗИНФЕКЦИИ", "p": [184] },
	{ "s": "ДЕЗИНФЕКЦИОННО", "p": [14] },
	{ "s": "ДЕЗИНФЕКЦИОННО-ДУШЕВЫЕ", "p": [14] },
	{ "s": "ДЕЗИНФЕКЦИОННЫХ", "p": [66] },
	{ "s": "ДЕЗИНФИЦИРУЮЩИМИ", "p": [42] },
	{ "s": "ДЕЗИНФИЦИРУЮЩИХ", "p": [61, 60, 57] },
	{ "s": "ДЕЙДВУДЕ", "p": [18] },
	{ "s": "ДЕЙДВУДНЫХ", "p": [11] },
	{ "s": "ДЕЙСТВИЕ", "p": [130] },
	{ "s": "ДЕЙСТВИЕМ", "p": [127] },
	{ "s": "ДЕЙСТВИЙ", "p": [47, 70, 37, 19, 187, 42, 11] },
	{ "s": "ДЕЙСТВИТЕЛЕН", "p": [86] },
	{ "s": "ДЕЙСТВИТЕЛЬНО", "p": [91] },
	{ "s": "ДЕЙСТВИТЕЛЬНОГО", "p": [106] },
	{ "s": "ДЕЙСТВИТЕЛЬНЫ", "p": [85] },
	{ "s": "ДЕЙСТВИТЕЛЬНЫМИ", "p": [84] },
	{ "s": "ДЕЙСТВИЮ", "p": [11] },
	{ "s": "ДЕЙСТВИЯ", "p": [182, 85, 91, 179, 128, 125, 123, 89, 66, 50, 47, 42, 38, 21, 19, 15] },
	{ "s": "ДЕЙСТВИЯМ", "p": [25] },
	{ "s": "ДЕЙСТВИЯМИ", "p": [11] },
	{ "s": "ДЕЙСТВИЯХ", "p": [19] },
	{ "s": "ДЕЙСТВУЮЩЕГО", "p": [188, 86] },
	{ "s": "ДЕЙСТВУЮЩЕЙ", "p": [85, 131, 84, 17] },
	{ "s": "ДЕЙСТВУЮЩИМ", "p": [132] },
	{ "s": "ДЕКАБРЬ", "p": [170, 111, 97, 84, 83] },
	{ "s": "ДЕКАБРЯ", "p": [9] },
	{ "s": "ДЕКОРАТИВНЫХ", "p": [184, 58] },
	{ "s": "ДЕЛ", "p": [73, 74, 191, 192, 70, 16] },
	{ "s": "ДЕЛА", "p": [74, 73, 192, 191] },
	{ "s": "ДЕЛАЕТ", "p": [91, 26, 21, 19] },
	{ "s": "ДЕЛАЕТСЯ", "p": [83, 82, 147, 100, 30, 86, 81, 73, 15] },
	{ "s": "ДЕЛАМ", "p": [2, 190, 84, 83, 20, 8, 4, 3, 1] },
	{ "s": "ДЕЛАТЬ", "p": [51] },
	{ "s": "ДЕЛАЮТ", "p": [85] },
	{ "s": "ДЕЛАЮТСЯ", "p": [83, 137, 132] },
	{ "s": "ДЕЛЕГИРОВАНО", "p": [71] },
	{ "s": "ДЕЛЕНИЯ", "p": [164] },
	{ "s": "ДЕЛИТСЯ", "p": [140] },
	{ "s": "ДЕЛОПРОИЗВОДСТВА", "p": [11] },
	{ "s": "ДЕЛОПРОИЗВОДСТВЕ", "p": [16] },
	{ "s": "ДЕЛОПРОИЗВОДСТВО", "p": [60] },
	{ "s": "ДЕЛУ", "p": [180] },
	{ "s": "ДЕЛЯТСЯ", "p": [149] },
	{ "s": "ДЕМОНТАЖ", "p": [137] },
	{ "s": "ДЕМОНТАЖА", "p": [14, 15] },
	{ "s": "ДЕМОНТИРОВАННЫЕ", "p": [33] },
	{ "s": "ДЕМОНТИРОВАННЫХ", "p": [165, 161, 137] },
	{ "s": "ДЕМОНТИРОВАНО", "p": [23] },
	{ "s": "ДЕМОНТИРОВАНЫ", "p": [33] },
	{ "s": "ДЕНЕЖНОМ", "p": [187] },
	{ "s": "ДЕНЕЖНЫЕ", "p": [188] },
	{ "s": "ДЕНЕЖНЫХ", "p": [11, 5, 192, 105, 74, 45, 16, 8] },
	{ "s": "ДЕНСИМЕТР", "p": [164, 133] },
	{ "s": "ДЕНЬ", "p": [83, 106, 66, 133, 73, 67, 42, 27, 26, 19] },
	{ "s": "ДЕПАРТАМЕНТ", "p": [3] },
	{ "s": "ДЕПАРТАМЕНТОМ", "p": [75] },
	{ "s": "ДЕПО", "p": [138, 164, 137, 135, 132, 25, 177, 166, 160, 150, 148, 145, 104, 24] },
	{ "s": "ДЕРАТИЗАЦИОННЫХ", "p": [66] },
	{ "s": "ДЕРЕВУ", "p": [174] },
	{ "s": "ДЕРЕВЬЕВ", "p": [58] },
	{ "s": "ДЕРЕВЯННАЯ", "p": [176] },
	{ "s": "ДЕРЕВЯННУЮ", "p": [127] },
	{ "s": "ДЕРЕВЯННЫЕ", "p": [138] },
	{ "s": "ДЕРЕВЯННЫЙ", "p": [127] },
	{ "s": "ДЕРЕВЯННЫМ", "p": [122] },
	{ "s": "ДЕРЕВЯННЫХ", "p": [148, 127] },
	{ "s": "ДЕРЖАТ", "p": [125] },
	{ "s": "ДЕРЖАТЕЛЬ", "p": [127] },
	{ "s": "ДЕРЖАТЕЛЯ", "p": [127] },
	{ "s": "ДЕРМАТИТЫ", "p": [182] },
	{ "s": "ДЕСАНТНУЮ", "p": [64] },
	{ "s": "ДЕТАЛЕЙ", "p": [25, 116, 24, 23, 137, 32, 165, 164, 161, 149, 84, 81, 33, 15] },
	{ "s": "ДЕТАЛИ", "p": [103, 33, 104, 83, 81, 80, 24, 14] },
	{ "s": "ДЕТАЛЬНЫЙ", "p": [187] },
	{ "s": "ДЕТАЛЬНЫХ", "p": [9] },
	{ "s": "ДЕТЕЙ", "p": [20] },
	{ "s": "ДЕТСКИЕ", "p": [20] },
	{ "s": "ДЕТСКИЙ", "p": [20] },
	{ "s": "ДЕТСКОГО", "p": [20] },
	{ "s": "ДЕФЕКТ", "p": [3] },
	{ "s": "ДЕФЕКТА", "p": [103] },
	{ "s": "ДЕФЕКТАЦИИ", "p": [24, 103] },
	{ "s": "ДЕФЕКТАЦИЯ", "p": [24] },
	{ "s": "ДЕФЕКТНАЯ", "p": [103, 24] },
	{ "s": "ДЕФЕКТНЫХ", "p": [77, 55, 25, 9] },
	{ "s": "ДЕФЕКТОВ", "p": [129, 125, 121, 118, 104, 85, 72, 25, 15, 11] },
	{ "s": "ДЕФЕКТЫ", "p": [172, 83, 24, 20, 15] },
	{ "s": "ДЕФОРМАЦИИ", "p": [127, 121] },
	{ "s": "ДЕФОРМАЦИЙ", "p": [121] },
	{ "s": "ДЕФОРМАЦИЯ", "p": [122] },
	{ "s": "ДЕЦЕНТРАЛИЗОВАННАЯ", "p": [33] },
	{ "s": "ДЕЦЕНТРАЛИЗОВАННОЕ", "p": [10] },
	{ "s": "ДЕЦЕНТРАЛИЗОВАННОМ", "p": [64] },
	{ "s": "ДЕЯТЕЛЬНОСТИ", "p": [11, 8, 19, 9, 20, 74, 66, 64, 61, 60, 59, 58, 57, 70, 67, 56, 16, 12, 6, 101, 92, 73, 27, 187, 147, 112, 106, 81, 69, 42, 13, 5, 4] },
	{ "s": "ДЕЯТЕЛЬНОСТЬ", "p": [65, 8, 73, 62, 55, 43, 13, 12, 11] },
	{ "s": "ДЕЯТЕЛЬНОСТЬЮ", "p": [73, 61, 60, 59, 58, 57, 19, 11] },
	{ "s": "ДИАГНОСТА", "p": [137] },
	{ "s": "ДИАГНОСТИКИ", "p": [14] },
	{ "s": "ДИАГНОСТИРОВАНИЕ", "p": [106, 25, 3] },
	{ "s": "ДИАГНОСТИРОВАНИЙ", "p": [106] },
	{ "s": "ДИАГНОСТИРОВАНИЮ", "p": [10] },
	{ "s": "ДИАГНОСТИРОВАНИЯ", "p": [137, 161, 33, 29, 25, 24, 11, 8] },
	{ "s": "ДИАГНОСТИЧЕСКАЯ", "p": [24] },
	{ "s": "ДИАГНОСТИЧЕСКИМИ", "p": [161] },
	{ "s": "ДИАГНОСТИЧЕСКИХ", "p": [25] },
	{ "s": "ДИАГНОСТИЧЕСКОГО", "p": [25, 11] },
	{ "s": "ДИАГНОСТИЧЕСКОЙ", "p": [161] },
	{ "s": "ДИАГОНАЛИ", "p": [186, 183] },
	{ "s": "ДИАМЕТР", "p": [118, 84, 131, 124, 120] },
	{ "s": "ДИАМЕТРА", "p": [130, 124] },
	{ "s": "ДИАМЕТРОВ", "p": [128, 123] },
	{ "s": "ДИАМЕТРОМ", "p": [130, 153, 152, 145, 126, 124, 122] },
	{ "s": "ДИАПАЗОН", "p": [164, 133] },
	{ "s": "ДИАПАЗОНАМ", "p": [52] },
	{ "s": "ДИАПАЗОНЕ", "p": [84] },
	{ "s": "ДИЕТИЧЕСКИХ", "p": [58] },
	{ "s": "ДИЗЕЛЬ", "p": [84] },
	{ "s": "ДИЗЕЛЬ-ГЕНЕРАТОР", "p": [84] },
	{ "s": "ДИЗЕЛЬНОГО", "p": [188] },
	{ "s": "ДИЗЕЛЬНОЕ", "p": [55] },
	{ "s": "ДИЗЕЛЬНЫМ", "p": [23, 21] },
	{ "s": "ДИЗЕЛЬНЫМИ", "p": [23] },
	{ "s": "ДИЗЕЛЬНЫХ", "p": [133, 55] },
	{ "s": "ДИНАМИКИ", "p": [184] },
	{ "s": "ДИНАМОМЕТРИЧЕСКАЯ", "p": [164] },
	{ "s": "ДИНАМОМЕТРИЧЕСКИЙ", "p": [133] },
	{ "s": "ДИРЕКТОРА", "p": [20] },
	{ "s": "ДИСК", "p": [116] },
	{ "s": "ДИСЛОКАЦИИ", "p": [42, 11, 190, 189, 187, 62, 36, 25, 23, 19] },
	{ "s": "ДИСЛОЦИРУЕМЫХ", "p": [115] },
	{ "s": "ДИСЛОЦИРУЮЩИХСЯ", "p": [188] },
	{ "s": "ДИСПЕТЧЕР", "p": [19] },
	{ "s": "ДИСПЕТЧЕРА", "p": [177, 156, 20] },
	{ "s": "ДИСПЕТЧЕРСКОГО", "p": [184, 57] },
	{ "s": "ДИСПЕТЧЕРСКОЙ", "p": [11] },
	{ "s": "ДИСПЕТЧЕРСКУЮ", "p": [20] },
	{ "s": "ДИСПЕТЧЕРЫ", "p": [133] },
	{ "s": "ДИСТАНЦИОННОГО", "p": [18] },
	{ "s": "ДИСТАНЦИОННЫМ", "p": [145, 134] },
	{ "s": "ДИСТИЛЛИРОВАННОЙ", "p": [140, 25, 164, 133] },
	{ "s": "ДИСТИЛЛЯТОРА", "p": [140] },
	{ "s": "ДИСТИЛЛЯЦИОННЫЕ", "p": [14] },
	{ "s": "ДИСЦИПЛИНЫ", "p": [38, 11] },
	{ "s": "ДИЭЛЕКТРИЧЕСКИЕ", "p": [140] },
	{ "s": "ДЛИН", "p": [84] },
	{ "s": "ДЛИНА", "p": [164, 84, 133, 131, 126, 118] },
	{ "s": "ДЛИНАХ", "p": [84] },
	{ "s": "ДЛИНЕ", "p": [184, 125] },
	{ "s": "ДЛИННОГУБЦЫ", "p": [164] },
	{ "s": "ДЛИННОЙ", "p": [164, 133] },
	{ "s": "ДЛИНОЙ", "p": [124, 133, 130, 122] },
	{ "s": "ДЛИНУ", "p": [122, 118, 139, 131, 124] },
	{ "s": "ДЛИНЫ", "p": [131, 122] },
	{ "s": "ДЛИТЕЛЬНОГО", "p": [23, 99, 98, 167, 140, 95, 25, 11] },
	{ "s": "ДЛИТЕЛЬНОЕ", "p": [23, 95, 83, 66] },
	{ "s": "ДЛИТЕЛЬНОЙ", "p": [120, 84] },
	{ "s": "ДЛИТЕЛЬНОМ", "p": [97, 23, 25, 105, 27, 19, 182, 171, 140, 138, 137, 125, 107, 106, 95, 83] },
	{ "s": "ДЛИТЕЛЬНОМУ", "p": [95] },
	{ "s": "ДЛИТЕЛЬНОСТИ", "p": [106] },
	{ "s": "ДЛИТЕЛЬНУЮ", "p": [3] },
	{ "s": "ДЛИТЕЛЬНЫМ", "p": [23] },
	{ "s": "ДЛЯ", "p": [184, 133, 140, 20, 58, 25, 11, 42, 137, 23, 164, 59, 19, 190, 188, 141, 27, 134, 125, 15, 138, 126, 118, 85, 61, 57, 14, 3, 146, 143, 79, 62, 60, 165, 161, 71, 64, 21, 135, 127, 84, 41, 187, 136, 132, 122, 115, 83, 82, 63, 26, 18, 147, 131, 121, 92, 55, 17, 9, 176, 124, 107, 105, 97, 66, 30, 24, 16, 10, 183, 177, 149, 148, 139, 116, 109, 106, 100, 56, 52, 50, 33, 178, 145, 144, 142, 130, 129, 128, 120, 112, 95, 90, 81, 73, 70, 48, 47, 29, 8, 189, 186, 185, 182, 181, 173, 171, 166, 162, 157, 155, 153, 113, 104, 101, 93, 91, 78, 77, 75, 74, 69, 67, 54, 49, 46, 45, 38, 37, 36, 34, 32, 28, 13, 12, 6, 4] },
	{ "s": "ДНЕВАЛЬНОГО", "p": [147] },
	{ "s": "ДНЕВАЛЬНОМУ", "p": [155] },
	{ "s": "ДНЕВАЛЬНЫЕ", "p": [147] },
	{ "s": "ДНЕВНОГО", "p": [184] },
	{ "s": "ДНЕЙ", "p": [34, 26, 106, 71, 66, 11, 108, 73, 67, 27, 9] },
	{ "s": "ДНЕЙ/МЕСЯЦЕВ", "p": [108] },
	{ "s": "ДНЕМ", "p": [184] },
	{ "s": "ДНИ", "p": [19, 106, 66, 85, 62, 57, 37, 26, 20, 11] },
	{ "s": "ДНЯ", "p": [147, 42, 184, 106, 86, 83, 71, 66, 64, 61, 60, 57, 50, 26, 21, 20, 19, 16] },
	{ "s": "ДНЯМ", "p": [106] },
	{ "s": "ДО", "p": [127, 11, 20, 164, 85, 25, 58, 9, 122, 84, 27, 184, 125, 42, 19, 160, 138, 124, 23, 190, 178, 148, 130, 107, 83, 80, 17, 154, 140, 121, 73, 57, 55, 45, 38, 188, 177, 166, 159, 136, 133, 131, 123, 118, 111, 108, 106, 98, 81, 78, 71, 69, 66, 61, 60, 59, 32, 28, 26, 18, 16, 8, 5] },
	{ "s": "ДОБАВКОЙ", "p": [23] },
	{ "s": "ДОБРОКАЧЕСТВЕННОГО", "p": [11] },
	{ "s": "ДОБЫЧИ", "p": [14, 3] },
	{ "s": "ДОВЕДЕНИЕ", "p": [11, 69, 61, 60, 59, 58, 57, 42] },
	{ "s": "ДОВЕДЕНИЕМ", "p": [42, 5] },
	{ "s": "ДОВЕДЕНИЯ", "p": [11, 10] },
	{ "s": "ДОВЕДЕННЫХ", "p": [11, 12] },
	{ "s": "ДОВЕРЕННОСТИ", "p": [67] },
	{ "s": "ДОВЕСТИ", "p": [190] },
	{ "s": "ДОВОДИТ", "p": [78, 42] },
	{ "s": "ДОВОДИТСЯ", "p": [27, 23] },
	{ "s": "ДОВОДЯТСЯ", "p": [148, 106, 46] },
	{ "s": "ДОВОЛЬСТВИЕ", "p": [190] },
	{ "s": "ДОВОЛЬСТВИЯ", "p": [11, 5, 192, 190, 141, 107, 42, 23, 14, 10, 9] },
	{ "s": "ДОВОЛЬСТВУЮЩИМ", "p": [83] },
	{ "s": "ДОВОЛЬСТВУЮЩИМИ", "p": [83] },
	{ "s": "ДОВОЛЬСТВУЮЩИХСЯ", "p": [42, 11] },
	{ "s": "ДОГОВОР", "p": [61, 60, 59, 58, 57] },
	{ "s": "ДОГОВОРА", "p": [17, 66, 34, 11] },
	{ "s": "ДОГОВОРАМИ", "p": [46, 45] },
	{ "s": "ДОГОВОРНОЙ", "p": [12, 84, 71, 66, 65, 32] },
	{ "s": "ДОГОВОРНЫХ", "p": [11] },
	{ "s": "ДОГОВОРОВ", "p": [55, 11, 62, 45] },
	{ "s": "ДОГОВОРОМ", "p": [11] },
	{ "s": "ДОГОВОРУ", "p": [19] },
	{ "s": "ДОГОВОРЫ", "p": [62] },
	{ "s": "ДОЖДЕВЫХ", "p": [144] },
	{ "s": "ДОЗ", "p": [63] },
	{ "s": "ДОЗА", "p": [182] },
	{ "s": "ДОЗАПРАВКА", "p": [62, 24] },
	{ "s": "ДОЗИМЕТРИЧЕСКОГО", "p": [63] },
	{ "s": "ДОЗИРОВАННОЙ", "p": [140] },
	{ "s": "ДОЗИРОВАННУЮ", "p": [134] },
	{ "s": "ДОЗНАНИЯ", "p": [20] },
	{ "s": "ДОК", "p": [11] },
	{ "s": "ДОКЛАД", "p": [187, 188, 108] },
	{ "s": "ДОКЛАДА", "p": [71] },
	{ "s": "ДОКЛАДОВ", "p": [73] },
	{ "s": "ДОКЛАДЫ", "p": [74] },
	{ "s": "ДОКЛАДЫВАЕТ", "p": [55, 74, 71, 15, 9] },
	{ "s": "ДОКУМЕНТ", "p": [83, 110, 172, 107, 106, 104, 97, 84, 82] },
	{ "s": "ДОКУМЕНТА", "p": [85, 110, 84, 86, 83, 82, 188, 127, 108, 107, 104, 51, 50, 16] },
	{ "s": "ДОКУМЕНТАЛЬНО", "p": [71] },
	{ "s": "ДОКУМЕНТАЛЬНОГО", "p": [15] },
	{ "s": "ДОКУМЕНТАЛЬНОЕ", "p": [73] },
	{ "s": "ДОКУМЕНТАЛЬНОЙ", "p": [70] },
	{ "s": "ДОКУМЕНТАЛЬНЫМ", "p": [190] },
	{ "s": "ДОКУМЕНТАМ", "p": [16, 15, 82, 81, 73, 71, 51, 11] },
	{ "s": "ДОКУМЕНТАМИ", "p": [15, 137, 85, 33, 27, 11, 131, 107, 105, 97, 55, 25, 19, 18, 3] },
	{ "s": "ДОКУМЕНТАХ", "p": [13, 115, 70, 64, 45] },
	{ "s": "ДОКУМЕНТАЦИЕЙ", "p": [138, 137, 136, 71, 15, 3, 173, 167, 162, 157, 140, 134, 118, 85, 84, 62, 52] },
	{ "s": "ДОКУМЕНТАЦИИ", "p": [85, 133, 13, 11, 157, 155, 167, 25, 18, 128, 125, 123, 118, 71, 42, 24, 19, 17, 15, 3, 138, 137, 131, 130, 129, 124, 122, 119, 111, 107, 105, 97, 95, 84, 58, 49, 21, 20] },
	{ "s": "ДОКУМЕНТАЦИЮ", "p": [118, 27, 25, 19] },
	{ "s": "ДОКУМЕНТАЦИЯ", "p": [162, 159, 173, 157, 137, 133, 155, 175, 174, 167, 161, 140, 81, 184, 141, 136, 135, 134, 104, 83, 79, 19] },
	{ "s": "ДОКУМЕНТЕ", "p": [84] },
	{ "s": "ДОКУМЕНТОВ", "p": [11, 16, 187, 184, 62, 83, 55, 25, 19, 3, 147, 141, 133, 132, 112, 84, 82, 81, 79, 78, 73, 69, 45, 42, 23, 20, 17, 13] },
	{ "s": "ДОКУМЕНТОМ", "p": [16, 83, 81, 73, 20, 9] },
	{ "s": "ДОКУМЕНТУ", "p": [64] },
	{ "s": "ДОКУМЕНТЫ", "p": [108, 16, 134, 133, 84, 81, 53, 27, 21, 19, 15] },
	{ "s": "ДОЛЖЕН", "p": [118, 147, 138, 73, 184, 180, 179, 148, 137, 134, 131, 127, 124, 123, 121, 115, 113, 69, 58, 56, 42, 38, 33, 32, 23, 18] },
	{ "s": "ДОЛЖНА", "p": [118, 138, 127, 184, 149, 125, 58, 136, 122, 145, 140, 124, 177, 146, 144, 141, 137, 131, 121, 115, 85, 84, 79, 71, 45, 42, 38, 25, 21] },
	{ "s": "ДОЛЖНО", "p": [121, 184, 141, 140, 138, 132, 130, 85, 79, 74, 62, 59, 58, 57, 27, 26, 25, 24, 23, 20] },
	{ "s": "ДОЛЖНОСТИ", "p": [73, 74, 192, 191, 184, 70, 43, 42, 19, 16] },
	{ "s": "ДОЛЖНОСТНОГО", "p": [83, 156, 85, 82, 158, 148, 147, 141, 108, 79, 20, 185, 145, 102, 100, 93, 84, 81, 74, 73, 59, 58, 27, 11] },
	{ "s": "ДОЛЖНОСТНОЕ", "p": [11, 114, 147, 89, 57, 188, 185, 184, 171, 148, 110, 85, 67, 61, 60, 59, 47, 41, 30, 27, 19, 12, 3] },
	{ "s": "ДОЛЖНОСТНОМ", "p": [11] },
	{ "s": "ДОЛЖНОСТНОМУ", "p": [19, 147, 49, 45, 20] },
	{ "s": "ДОЛЖНОСТНЫЕ", "p": [11, 147, 23, 15, 133, 171, 112, 83, 78, 73, 70, 62, 56, 42, 38, 27, 25, 19, 12, 9, 8] },
	{ "s": "ДОЛЖНОСТНЫМ", "p": [83, 133, 86, 69, 50, 42, 27, 169, 113, 111, 100, 78, 47, 30, 21] },
	{ "s": "ДОЛЖНОСТНЫМИ", "p": [73, 24, 101, 11, 85, 83, 70, 20, 167, 140, 132, 69, 50, 42, 30, 19, 9, 8] },
	{ "s": "ДОЛЖНОСТНЫХ", "p": [11, 20, 74, 133, 132, 47, 147, 73, 69, 36, 30, 190, 171, 166, 157, 155, 134, 70, 61, 60, 57, 50, 43, 41, 23, 19, 9, 8] },
	{ "s": "ДОЛЖНОСТЬ", "p": [83, 73, 81, 192, 84, 74, 108, 112, 191, 114, 180, 110, 85, 171, 170, 169, 166, 163, 131, 113, 111, 107, 106, 105, 102, 100, 97, 95, 92, 89, 87, 86, 82, 78, 77, 76] },
	{ "s": "ДОЛЖНЫ", "p": [184, 85, 138, 141, 140, 118, 79, 58, 144, 128, 137, 124, 23, 136, 132, 125, 123, 59, 130, 84, 42, 25, 186, 180, 179, 148, 134, 129, 121, 119, 74, 66, 63, 50, 41, 35, 18] },
	{ "s": "ДОЛИВ", "p": [25] },
	{ "s": "ДОЛОЖИТЬ", "p": [20] },
	{ "s": "ДОЛЯ", "p": [177] },
	{ "s": "ДОМКРАТ", "p": [164] },
	{ "s": "ДОМКРАТАМИ", "p": [137] },
	{ "s": "ДОНЕСЕНИЕ", "p": [33] },
	{ "s": "ДОНЕСЕНИЕМ", "p": [55, 9] },
	{ "s": "ДОНЕСЕНИЙ", "p": [55, 16, 187, 33, 27, 25, 9] },
	{ "s": "ДОНЕСЕНИЯ", "p": [27] },
	{ "s": "ДОННОЙ", "p": [11] },
	{ "s": "ДООБОРУДОВАНИЕ", "p": [18] },
	{ "s": "ДОПОДГОТОВКИ", "p": [19] },
	{ "s": "ДОПОЛНИТЕЛЬНАЯ", "p": [118, 159, 150, 131, 26] },
	{ "s": "ДОПОЛНИТЕЛЬНО", "p": [25, 140, 133, 132, 184, 147, 141, 138, 137, 136, 131, 130, 124, 120, 104, 79, 76] },
	{ "s": "ДОПОЛНИТЕЛЬНОГО", "p": [24, 18] },
	{ "s": "ДОПОЛНИТЕЛЬНОЙ", "p": [118, 187] },
	{ "s": "ДОПОЛНИТЕЛЬНОМ", "p": [187, 83] },
	{ "s": "ДОПОЛНИТЕЛЬНУЮ", "p": [120, 118] },
	{ "s": "ДОПОЛНИТЕЛЬНЫЕ", "p": [96, 141, 128, 118, 111, 84, 82, 79, 62, 46, 26, 23] },
	{ "s": "ДОПОЛНИТЕЛЬНЫМИ", "p": [26] },
	{ "s": "ДОПОЛНИТЕЛЬНЫХ", "p": [20, 188, 107, 96, 84, 76, 25, 19] },
	{ "s": "ДОПУСК", "p": [147, 74, 18] },
	{ "s": "ДОПУСКА", "p": [147, 91, 37, 24] },
	{ "s": "ДОПУСКАЕМЫЙ", "p": [47] },
	{ "s": "ДОПУСКАЕТ", "p": [85, 66] },
	{ "s": "ДОПУСКАЕТСЯ", "p": [19, 23, 85, 137, 125, 106, 42, 20, 138, 128, 120, 105, 61, 58, 25, 184, 169, 168, 161, 150, 149, 147, 145, 133, 130, 123, 118, 115, 107, 104, 100, 96, 86, 83, 62, 57, 52, 45, 33, 27, 26, 18, 16] },
	{ "s": "ДОПУСКАТЬ", "p": [124] },
	{ "s": "ДОПУСКАЮТСЯ", "p": [85, 19, 147, 131, 124, 84, 83, 49] },
	{ "s": "ДОПУСКАЮЩЕЕ", "p": [3] },
	{ "s": "ДОПУСКАЯ", "p": [124] },
	{ "s": "ДОПУСКЕ", "p": [85, 19] },
	{ "s": "ДОПУСКИ", "p": [188] },
	{ "s": "ДОПУСКОМ", "p": [60] },
	{ "s": "ДОПУСТИВШЕГО", "p": [11] },
	{ "s": "ДОПУСТИВШИЕ", "p": [30] },
	{ "s": "ДОПУСТИМАЯ", "p": [126] },
	{ "s": "ДОПУСТИМЫЕ", "p": [18] },
	{ "s": "ДОПУСТИМЫЙ", "p": [32] },
	{ "s": "ДОПУСТИМЫХ", "p": [63] },
	{ "s": "ДОПУЩЕН", "p": [91, 89, 19] },
	{ "s": "ДОПУЩЕНА", "p": [188] },
	{ "s": "ДОПУЩЕННЫМ", "p": [184, 50] },
	{ "s": "ДОПУЩЕННЫМИ", "p": [20, 18] },
	{ "s": "ДОПУЩЕННЫХ", "p": [83, 50, 48, 19] },
	{ "s": "ДОРАБОТКАХ", "p": [11] },
	{ "s": "ДОРАБОТКИ", "p": [72, 15] },
	{ "s": "ДОРАБОТОК", "p": [11, 81, 23] },
	{ "s": "ДОРОГ", "p": [144] },
	{ "s": "ДОРОГЕ", "p": [124, 83, 45] },
	{ "s": "ДОРОГИ", "p": [144, 146, 132, 58] },
	{ "s": "ДОРОЖКАМИ", "p": [61, 57] },
	{ "s": "ДОРОЖКИ", "p": [140, 138] },
	{ "s": "ДОРОЖНО", "p": [179, 144, 91, 3] },
	{ "s": "ДОРОЖНО-СИГНАЛЬНЫМИ", "p": [144] },
	{ "s": "ДОРОЖНО-ТРАНСПОРТНОГО", "p": [91] },
	{ "s": "ДОРОЖНО-ТРАНСПОРТНОЕ", "p": [3] },
	{ "s": "ДОРОЖНО-ТРАНСПОРТНЫХ", "p": [179] },
	{ "s": "ДОРОЖНОГО", "p": [19, 181, 180, 91, 8, 3] },
	{ "s": "ДОРОЖНОЙ", "p": [133] },
	{ "s": "ДОРОЖНОМ", "p": [24] },
	{ "s": "ДОРОЖНЫЕ", "p": [179, 133, 14] },
	{ "s": "ДОРОЖНЫХ", "p": [133, 190, 181, 167, 138, 38, 3] },
	{ "s": "ДОСКУ", "p": [127] },
	{ "s": "ДОСРОЧНОГО", "p": [81] },
	{ "s": "ДОСРОЧНОМ", "p": [66] },
	{ "s": "ДОСТАВКА", "p": [188, 78] },
	{ "s": "ДОСТАВКЕ", "p": [64] },
	{ "s": "ДОСТАВКИ", "p": [20, 9, 62, 42, 32, 23, 8] },
	{ "s": "ДОСТАВКОЙ", "p": [42] },
	{ "s": "ДОСТАВКУ", "p": [190, 67, 62, 42, 11] },
	{ "s": "ДОСТАВЛЕННОЙ", "p": [64] },
	{ "s": "ДОСТАВЛЕННЫЕ", "p": [125, 121] },
	{ "s": "ДОСТАВЛЕННЫХ", "p": [64] },
	{ "s": "ДОСТАВЛЯЕМЫХ", "p": [64] },
	{ "s": "ДОСТАВЛЯЕТСЯ", "p": [83] },
	{ "s": "ДОСТАВЛЯЮЩЕГО", "p": [66] },
	{ "s": "ДОСТАТОЧНО", "p": [125, 58] },
	{ "s": "ДОСТАТОЧНОЕ", "p": [184] },
	{ "s": "ДОСТАТОЧНОМ", "p": [58, 42] },
	{ "s": "ДОСТАТОЧНЫМ", "p": [184, 38] },
	{ "s": "ДОСТАТОЧНЫМИ", "p": [138] },
	{ "s": "ДОСТИГАЕТСЯ", "p": [148, 132, 29, 23] },
	{ "s": "ДОСТИГНУТЫЕ", "p": [37] },
	{ "s": "ДОСТИЖЕНИЕ", "p": [13] },
	{ "s": "ДОСТИЖЕНИЯ", "p": [13] },
	{ "s": "ДОСТОВЕРНОГО", "p": [11] },
	{ "s": "ДОСТОВЕРНОЙ", "p": [16] },
	{ "s": "ДОСТОВЕРНОСТИ", "p": [13] },
	{ "s": "ДОСТОВЕРНОСТЬ", "p": [66] },
	{ "s": "ДОСТУП", "p": [148] },
	{ "s": "ДОСТУПА", "p": [50] },
	{ "s": "ДОСТУПНОСТИ", "p": [8] },
	{ "s": "ДОСУГА", "p": [184, 59, 58] },
	{ "s": "ДОУКОМПЛЕКТОВАНИЕ", "p": [105] },
	{ "s": "ДОХОД", "p": [64, 12] },
	{ "s": "ДОЧИСТКИ", "p": [42] },
	{ "s": "ДОШКОЛЬНЫЕ", "p": [20] },
	{ "s": "ДР", "p": [147, 25, 172, 137, 111, 106, 105, 95, 83, 11] },
	{ "s": "ДРАГОЦЕННЫХ", "p": [11, 82] },
	{ "s": "ДРЕЛЬ", "p": [164] },
	{ "s": "ДРЕНАЖ", "p": [144, 132] },
	{ "s": "ДРОБИ", "p": [118] },
	{ "s": "ДРОБЬ", "p": [169, 106] },
	{ "s": "ДРОБЬЮ", "p": [85, 83] },
	{ "s": "ДРОВА", "p": [55] },
	{ "s": "ДРУГ", "p": [141, 138, 79] },
	{ "s": "ДРУГА", "p": [141, 138, 79] },
	{ "s": "ДРУГАЯ", "p": [161, 137, 136, 104, 45] },
	{ "s": "ДРУГИЕ", "p": [3, 133, 124, 83, 15, 192, 187, 184, 137, 125, 112, 105, 104, 74, 66, 58, 57, 56, 52, 42, 25, 19, 16] },
	{ "s": "ДРУГИМ", "p": [132, 124, 122, 85, 74, 62, 42, 17, 9] },
	{ "s": "ДРУГИМИ", "p": [15, 148, 133, 130, 21, 19, 10] },
	{ "s": "ДРУГИХ", "p": [11, 184, 147, 25, 19, 42, 29, 23, 128, 83, 69, 66, 63, 45, 30, 192, 190, 187, 171, 145, 137, 133, 126, 125, 124, 123, 122, 85, 82, 75, 74, 73, 70, 62, 58, 56, 46, 35, 20, 17, 16, 15, 6] },
	{ "s": "ДРУГОГО", "p": [11, 184, 62, 20, 18] },
	{ "s": "ДРУГОЕ", "p": [83, 58, 184, 125, 59, 81, 25, 3] },
	{ "s": "ДРУГОЙ", "p": [45, 187, 147, 121, 83, 184, 130, 125, 108, 86, 85, 42, 19, 18, 17, 16, 15, 11] },
	{ "s": "ДРУГОМ", "p": [127] },
	{ "s": "ДРУГОМУ", "p": [83] },
	{ "s": "ДРУГУЮ", "p": [85, 130, 126, 72, 58] },
	{ "s": "ДТО", "p": [8, 62, 11, 9, 112, 45, 38, 12, 42, 27, 20, 15, 3] },
	{ "s": "ДТП", "p": [179, 38, 181, 91, 11, 43, 21, 3] },
	{ "s": "ДУБЛИКАТ", "p": [83, 30] },
	{ "s": "ДУБЛИКАТА", "p": [83] },
	{ "s": "ДУБЛИКАТОВ", "p": [16] },
	{ "s": "ДУШ", "p": [189, 57] },
	{ "s": "ДУШЕВАЯ", "p": [184, 140, 61, 60, 59, 58] },
	{ "s": "ДУШЕВОЙ", "p": [184, 59, 58] },
	{ "s": "ДУШЕВУЮ", "p": [137] },
	{ "s": "ДУШЕВЫЕ", "p": [14, 188, 184, 142] },
	{ "s": "ДУШЕВЫХ", "p": [184, 188] },
	{ "s": "ДЫМА", "p": [184] },
	{ "s": "ДЫМНОСТИ", "p": [133] },
	{ "s": "ДЫМОМЕР", "p": [133] },
	{ "s": "ДЫХАНИЯ", "p": [61] },
	{ "s": "ДЫХАТЕЛЬНЫХ", "p": [182] },
	{ "s": "ДЮЙМОВОЙ", "p": [164] }
]